{"id": 1138, "year": 2020, "name": "Buffalo", "record": {"overall": [19, 12], "conf": [11, 8], "home": [9, 7], "road": [10, 5], "quad_1": [1, 0], "quad_2": [3, 3], "quad_3": [8, 5], "quad_4": [7, 4]}, "quad_wins": {"1": [{"opp_id": 1103, "team_score": 77, "opp_score": 74, "team_loc": "A", "date_int": 85, "date_str": "01/28", "conf": true}], "2": [{"opp_id": 1177, "team_score": 74, "opp_score": 69, "team_loc": "A", "date_int": 34, "date_str": "12/08", "conf": false}, {"opp_id": 1405, "team_score": 83, "opp_score": 67, "team_loc": "A", "date_int": 103, "date_str": "02/15", "conf": true}, {"opp_id": 1245, "team_score": 104, "opp_score": 98, "team_loc": "A", "date_int": 110, "date_str": "02/22", "conf": true}], "3": [{"opp_id": 1217, "team_score": 88, "opp_score": 76, "team_loc": "N", "date_int": 12, "date_str": "11/16", "conf": false}, {"opp_id": 1406, "team_score": 76, "opp_score": 73, "team_loc": "N", "date_int": 18, "date_str": "11/22", "conf": false}, {"opp_id": 1283, "team_score": 75, "opp_score": 74, "team_loc": "N", "date_int": 20, "date_str": "11/24", "conf": false}, {"opp_id": 1382, "team_score": 84, "opp_score": 79, "team_loc": "H", "date_int": 56, "date_str": "12/30", "conf": false}, {"opp_id": 1275, "team_score": 83, "opp_score": 78, "team_loc": "A", "date_int": 67, "date_str": "01/10", "conf": true}, {"opp_id": 1141, "team_score": 86, "opp_score": 67, "team_loc": "A", "date_int": 75, "date_str": "01/18", "conf": true}, {"opp_id": 1123, "team_score": 72, "opp_score": 59, "team_loc": "H", "date_int": 106, "date_str": "02/18", "conf": true}, {"opp_id": 1132, "team_score": 88, "opp_score": 84, "team_loc": "A", "date_int": 123, "date_str": "03/06", "conf": true}], "4": [{"opp_id": 1456, "team_score": 88, "opp_score": 77, "team_loc": "H", "date_int": 26, "date_str": "11/30", "conf": false}, {"opp_id": 1145, "team_score": 82, "opp_score": 73, "team_loc": "H", "date_int": 44, "date_str": "12/18", "conf": false}, {"opp_id": 1310, "team_score": 92, "opp_score": 72, "team_loc": "H", "date_int": 47, "date_str": "12/21", "conf": false}, {"opp_id": 1325, "team_score": 76, "opp_score": 73, "team_loc": "H", "date_int": 71, "date_str": "01/14", "conf": true}, {"opp_id": 1444, "team_score": 90, "opp_score": 79, "team_loc": "H", "date_int": 78, "date_str": "01/21", "conf": true}, {"opp_id": 1141, "team_score": 65, "opp_score": 60, "team_loc": "H", "date_int": 96, "date_str": "02/08", "conf": true}, {"opp_id": 1275, "team_score": 75, "opp_score": 69, "team_loc": "H", "date_int": 120, "date_str": "03/03", "conf": true}]}, "quad_losses": {"1": [], "2": [{"opp_id": 1163, "team_score": 68, "opp_score": 79, "team_loc": "N", "date_int": 17, "date_str": "11/21", "conf": false}, {"opp_id": 1123, "team_score": 68, "opp_score": 88, "team_loc": "A", "date_int": 64, "date_str": "01/07", "conf": true}, {"opp_id": 1103, "team_score": 73, "opp_score": 86, "team_loc": "H", "date_int": 117, "date_str": "02/29", "conf": true}], "3": [{"opp_id": 1435, "team_score": 76, "opp_score": 90, "team_loc": "A", "date_int": 29, "date_str": "12/03", "conf": false}, {"opp_id": 1245, "team_score": 66, "opp_score": 70, "team_loc": "H", "date_int": 81, "date_str": "01/24", "conf": true}, {"opp_id": 1132, "team_score": 77, "opp_score": 78, "team_loc": "H", "date_int": 88, "date_str": "01/31", "conf": true}, {"opp_id": 1185, "team_score": 62, "opp_score": 66, "team_loc": "A", "date_int": 92, "date_str": "02/04", "conf": true}, {"opp_id": 1325, "team_score": 69, "opp_score": 80, "team_loc": "A", "date_int": 113, "date_str": "02/25", "conf": true}], "4": [{"opp_id": 1171, "team_score": 63, "opp_score": 68, "team_loc": "H", "date_int": 4, "date_str": "11/08", "conf": false}, {"opp_id": 1119, "team_score": 76, "opp_score": 89, "team_loc": "H", "date_int": 40, "date_str": "12/14", "conf": false}, {"opp_id": 1296, "team_score": 72, "opp_score": 73, "team_loc": "H", "date_int": 61, "date_str": "01/04", "conf": true}, {"opp_id": 1275, "team_score": 79, "opp_score": 85, "team_loc": "H", "date_int": 126, "date_str": "03/09", "conf": true}]}, "conf": "mac", "stat_rankings": {"Points": 20, "Poss": 10, "OE": 123, "DE": 166, "NE": 145, "FGM": 7, "FGA": 1, "FGM3": 100, "FGA3": 49, "FTM": 223, "FTA": 195, "OR": 2, "DR": 40, "Ast": 48, "TO": 113, "Stl": 57, "Blk": 30, "Fouls": 89, "FG%": 200, "FG3%": 260, "FT%": 255, "OppPoints": 44, "OppFGM": 39, "OppFGA": 10, "OppFGM3": 219, "OppFGA3": 177, "OppFTM": 113, "OppFTA": 133, "OppOR": 48, "OppDR": 69, "OppAst": 147, "OppTO": 70, "OppStl": 101, "OppBlk": 39, "OppFouls": 173, "OppFG%": 163, "OppFG3%": 266, "OppFT%": 46, "AdjOE": 113, "AdjDE": 147, "AdjNE": 153, "SOS": 123, "SOV": 48}, "stats": {"Points": 77.645, "Poss": 75.2, "OE": 103.284, "DE": 101.003, "NE": 2.281, "FGM": 28.613, "FGA": 66.71, "FGM3": 7.903, "FGA3": 25.097, "FTM": 12.516, "FTA": 18.29, "OR": 14.355, "DR": 27.516, "Ast": 14.452, "TO": 13.806, "Stl": 7.516, "Blk": 4.581, "Fouls": 18.871, "FG%": 0.43, "FG3%": 0.313, "FT%": 0.681, "OppPoints": 75.903, "OppFGM": 27.516, "OppFGA": 63.226, "OppFGM3": 6.774, "OppFGA3": 21.613, "OppFTM": 14.097, "OppFTA": 19.226, "OppOR": 11.129, "OppDR": 27.032, "OppAst": 12.968, "OppTO": 14.323, "OppStl": 6.742, "OppBlk": 3.839, "OppFouls": 17.839, "OppFG%": 0.436, "OppFG3%": 0.315, "OppFT%": 0.736, "AdjOE": 105.025, "AdjDE": 103.51, "AdjNE": 1.515}, "coach": "jim_whitesell", "win_pct": 0.613, "sos": 0.513, "sov": 0.511, "ordinal_data": {"NET": 140}, "tournament": null, "similar_teams": []}