{"id": 1253, "year": 2025, "name": "Long Beach St", "record": {"overall": [5, 25], "conf": [3, 17], "home": [1, 11], "road": [4, 14], "quad_1": [0, 4], "quad_2": [0, 5], "quad_3": [2, 9], "quad_4": [3, 7]}, "quad_wins": {"1": [], "2": [], "3": [{"opp_id": 1337, "team_score": 79, "opp_score": 76, "team_loc": "A", "date_int": 45, "date_str": "12/19", "conf": false}, {"opp_id": 1413, "team_score": 84, "opp_score": 73, "team_loc": "A", "date_int": 68, "date_str": "01/11", "conf": true}], "4": [{"opp_id": 1168, "team_score": 73, "opp_score": 56, "team_loc": "A", "date_int": 31, "date_str": "12/05", "conf": true}, {"opp_id": 1218, "team_score": 76, "opp_score": 68, "team_loc": "H", "date_int": 33, "date_str": "12/07", "conf": true}, {"opp_id": 1360, "team_score": 76, "opp_score": 70, "team_loc": "A", "date_int": 36, "date_str": "12/10", "conf": false}]}, "quad_losses": {"1": [{"opp_id": 1362, "team_score": 54, "opp_score": 84, "team_loc": "A", "date_int": 9, "date_str": "11/13", "conf": false}, {"opp_id": 1211, "team_score": 41, "opp_score": 84, "team_loc": "A", "date_int": 16, "date_str": "11/20", "conf": false}, {"opp_id": 1414, "team_score": 60, "opp_score": 70, "team_loc": "A", "date_int": 117, "date_str": "03/01", "conf": true}, {"opp_id": 1471, "team_score": 63, "opp_score": 70, "team_loc": "A", "date_int": 122, "date_str": "03/06", "conf": true}], "2": [{"opp_id": 1355, "team_score": 79, "opp_score": 80, "team_loc": "A", "date_int": 4, "date_str": "11/08", "conf": false}, {"opp_id": 1471, "team_score": 54, "opp_score": 80, "team_loc": "H", "date_int": 73, "date_str": "01/16", "conf": true}, {"opp_id": 1169, "team_score": 76, "opp_score": 86, "team_loc": "A", "date_int": 80, "date_str": "01/23", "conf": true}, {"opp_id": 1414, "team_score": 75, "opp_score": 80, "team_loc": "H", "date_int": 87, "date_str": "01/30", "conf": true}, {"opp_id": 1415, "team_score": 66, "opp_score": 87, "team_loc": "A", "date_int": 108, "date_str": "02/20", "conf": true}], "3": [{"opp_id": 1422, "team_score": 48, "opp_score": 71, "team_loc": "N", "date_int": 21, "date_str": "11/25", "conf": false}, {"opp_id": 1431, "team_score": 44, "opp_score": 70, "team_loc": "N", "date_int": 22, "date_str": "11/26", "conf": false}, {"opp_id": 1363, "team_score": 66, "opp_score": 82, "team_loc": "N", "date_int": 23, "date_str": "11/27", "conf": false}, {"opp_id": 1415, "team_score": 60, "opp_score": 76, "team_loc": "H", "date_int": 59, "date_str": "01/02", "conf": true}, {"opp_id": 1142, "team_score": 69, "opp_score": 78, "team_loc": "A", "date_int": 82, "date_str": "01/25", "conf": true}, {"opp_id": 1364, "team_score": 54, "opp_score": 85, "team_loc": "A", "date_int": 89, "date_str": "02/01", "conf": true}, {"opp_id": 1169, "team_score": 80, "opp_score": 81, "team_loc": "H", "date_int": 96, "date_str": "02/08", "conf": true}, {"opp_id": 1218, "team_score": 60, "opp_score": 62, "team_loc": "A", "date_int": 101, "date_str": "02/13", "conf": true}, {"opp_id": 1364, "team_score": 56, "opp_score": 58, "team_loc": "H", "date_int": 110, "date_str": "02/22", "conf": true}], "4": [{"opp_id": 1339, "team_score": 61, "opp_score": 63, "team_loc": "H", "date_int": 12, "date_str": "11/16", "conf": false}, {"opp_id": 1201, "team_score": 69, "opp_score": 72, "team_loc": "H", "date_int": 19, "date_str": "11/23", "conf": false}, {"opp_id": 1167, "team_score": 65, "opp_score": 80, "team_loc": "A", "date_int": 61, "date_str": "01/04", "conf": true}, {"opp_id": 1168, "team_score": 67, "opp_score": 83, "team_loc": "H", "date_int": 75, "date_str": "01/18", "conf": true}, {"opp_id": 1413, "team_score": 65, "opp_score": 73, "team_loc": "H", "date_int": 94, "date_str": "02/06", "conf": true}, {"opp_id": 1167, "team_score": 87, "opp_score": 88, "team_loc": "H", "date_int": 115, "date_str": "02/27", "conf": true}, {"opp_id": 1142, "team_score": 69, "opp_score": 83, "team_loc": "H", "date_int": 124, "date_str": "03/08", "conf": true}]}, "conf": "big_west", "stat_rankings": {"Points": 327, "Poss": 274, "OE": 321, "DE": 337, "NE": 335, "FGM": 347, "FGA": 357, "FGM3": 258, "FGA3": 304, "FTM": 154, "FTA": 206, "OR": 318, "DR": 340, "Ast": 320, "TO": 36, "Stl": 317, "Blk": 232, "Fouls": 71, "FG%": 258, "FG3%": 105, "EFG%": 260, "FT%": 79, "OppPoints": 101, "OppFGM": 132, "OppFGA": 227, "OppFGM3": 97, "OppFGA3": 241, "OppFTM": 109, "OppFTA": 133, "OppOR": 80, "OppDR": 309, "OppAst": 203, "OppTO": 208, "OppStl": 94, "OppBlk": 326, "OppFouls": 97, "OppFG%": 78, "OppFG3%": 12, "OppEFG%": 65, "OppFT%": 62, "AdjOE": 287, "AdjDE": 280, "AdjNE": 285, "SOS": 141, "SOV": 340}, "stats": {"Points": 65.867, "Poss": 67.633, "OE": 97.319, "DE": 111.911, "NE": -14.592, "FGM": 22.433, "FGA": 52.6, "FGM3": 6.9, "FGA3": 19.533, "FTM": 14.1, "FTA": 18.667, "OR": 7.0, "DR": 20.2, "Ast": 11.067, "TO": 12.967, "Stl": 5.367, "Blk": 2.933, "Fouls": 18.333, "FG%": 0.429, "FG3%": 0.35, "EFG%": 0.494, "FT%": 0.751, "OppPoints": 75.633, "OppFGM": 26.333, "OppFGA": 56.933, "OppFGM3": 8.167, "OppFGA3": 21.433, "OppFTM": 14.8, "OppFTA": 20.067, "OppOR": 9.467, "OppDR": 20.867, "OppAst": 13.0, "OppTO": 10.833, "OppStl": 7.267, "OppBlk": 2.633, "OppFouls": 17.933, "OppFG%": 0.464, "OppFG3%": 0.379, "OppEFG%": 0.535, "OppFT%": 0.745, "AdjOE": 96.739, "AdjDE": 112.683, "AdjNE": -15.944}, "coach": "chris_acker", "win_pct": 0.167, "sos": 0.508, "sov": 0.305, "ordinal_data": {"NET": 326}, "tournament": null, "similar_teams": [{"id": 1179, "year": 2016, "avg": 0.991, "res": 0.994, "st": 0.988, "er": null}, {"id": 1150, "year": 2018, "avg": 0.99, "res": 0.996, "st": 0.984, "er": null}, {"id": 1198, "year": 2017, "avg": 0.988, "res": 0.989, "st": 0.987, "er": null}, {"id": 1461, "year": 2019, "avg": 0.988, "res": 0.992, "st": 0.983, "er": null}, {"id": 1303, "year": 2022, "avg": 0.988, "res": 0.986, "st": 0.99, "er": null}, {"id": 1379, "year": 2022, "avg": 0.987, "res": 0.998, "st": 0.976, "er": null}, {"id": 1226, "year": 2019, "avg": 0.986, "res": 0.986, "st": 0.987, "er": null}, {"id": 1178, "year": 2018, "avg": 0.986, "res": 0.996, "st": 0.977, "er": null}, {"id": 1265, "year": 2018, "avg": 0.986, "res": 0.988, "st": 0.984, "er": null}, {"id": 1107, "year": 2023, "avg": 0.986, "res": 0.994, "st": 0.978, "er": null}]}