{"id": 1285, "year": 2003, "name": "Montana", "record": {"overall": [12, 16], "conf": [7, 8], "home": [7, 5], "road": [5, 11], "quad_1": [1, 3], "quad_2": [0, 3], "quad_3": [2, 6], "quad_4": [9, 4]}, "quad_wins": {"1": [{"opp_id": 1390, "team_score": 70, "opp_score": 68, "team_loc": "A", "date_int": 42, "date_str": "12/16", "conf": false}], "2": [], "3": [{"opp_id": 1258, "team_score": 75, "opp_score": 68, "team_loc": "A", "date_int": 47, "date_str": "12/21", "conf": false}, {"opp_id": 1226, "team_score": 90, "opp_score": 88, "team_loc": "A", "date_int": 73, "date_str": "01/16", "conf": true}], "4": [{"opp_id": 1176, "team_score": 75, "opp_score": 47, "team_loc": "H", "date_int": 22, "date_str": "11/26", "conf": false}, {"opp_id": 1225, "team_score": 81, "opp_score": 69, "team_loc": "H", "date_int": 38, "date_str": "12/12", "conf": false}, {"opp_id": 1381, "team_score": 81, "opp_score": 61, "team_loc": "H", "date_int": 56, "date_str": "12/30", "conf": false}, {"opp_id": 1340, "team_score": 61, "opp_score": 49, "team_loc": "H", "date_int": 68, "date_str": "01/11", "conf": true}, {"opp_id": 1170, "team_score": 66, "opp_score": 59, "team_loc": "H", "date_int": 89, "date_str": "02/01", "conf": true}, {"opp_id": 1340, "team_score": 67, "opp_score": 49, "team_loc": "A", "date_int": 94, "date_str": "02/06", "conf": true}, {"opp_id": 1226, "team_score": 69, "opp_score": 65, "team_loc": "H", "date_int": 103, "date_str": "02/15", "conf": true}, {"opp_id": 1286, "team_score": 66, "opp_score": 63, "team_loc": "H", "date_int": 110, "date_str": "02/22", "conf": true}, {"opp_id": 1170, "team_score": 77, "opp_score": 71, "team_loc": "A", "date_int": 115, "date_str": "02/27", "conf": true}]}, "quad_losses": {"1": [{"opp_id": 1277, "team_score": 60, "opp_score": 80, "team_loc": "N", "date_int": 24, "date_str": "11/28", "conf": false}, {"opp_id": 1345, "team_score": 66, "opp_score": 84, "team_loc": "A", "date_int": 61, "date_str": "01/04", "conf": false}, {"opp_id": 1451, "team_score": 73, "opp_score": 97, "team_loc": "A", "date_int": 75, "date_str": "01/18", "conf": true}], "2": [{"opp_id": 1211, "team_score": 67, "opp_score": 75, "team_loc": "H", "date_int": 31, "date_str": "12/05", "conf": false}, {"opp_id": 1186, "team_score": 72, "opp_score": 87, "team_loc": "A", "date_int": 96, "date_str": "02/08", "conf": true}, {"opp_id": 1451, "team_score": 72, "opp_score": 75, "team_loc": "H", "date_int": 101, "date_str": "02/13", "conf": true}], "3": [{"opp_id": 1450, "team_score": 61, "opp_score": 73, "team_loc": "A", "date_int": 36, "date_str": "12/10", "conf": false}, {"opp_id": 1337, "team_score": 69, "opp_score": 86, "team_loc": "N", "date_int": 43, "date_str": "12/17", "conf": false}, {"opp_id": 1176, "team_score": 54, "opp_score": 62, "team_loc": "A", "date_int": 59, "date_str": "01/02", "conf": false}, {"opp_id": 1186, "team_score": 62, "opp_score": 72, "team_loc": "H", "date_int": 66, "date_str": "01/09", "conf": true}, {"opp_id": 1286, "team_score": 58, "opp_score": 62, "team_loc": "A", "date_int": 82, "date_str": "01/25", "conf": true}, {"opp_id": 1319, "team_score": 59, "opp_score": 69, "team_loc": "A", "date_int": 117, "date_str": "03/01", "conf": true}], "4": [{"opp_id": 1320, "team_score": 71, "opp_score": 77, "team_loc": "H", "date_int": 18, "date_str": "11/22", "conf": false}, {"opp_id": 1258, "team_score": 62, "opp_score": 65, "team_loc": "N", "date_int": 25, "date_str": "11/29", "conf": false}, {"opp_id": 1319, "team_score": 93, "opp_score": 97, "team_loc": "H", "date_int": 87, "date_str": "01/30", "conf": true}, {"opp_id": 1170, "team_score": 75, "opp_score": 88, "team_loc": "N", "date_int": 124, "date_str": "03/08", "conf": true}]}, "conf": "big_sky", "stat_rankings": {"Points": 169, "Poss": 188, "OE": 151, "DE": 244, "NE": 204, "FGM": 177, "FGA": 149, "FGM3": 38, "FGA3": 37, "FTM": 212, "FTA": 235, "OR": 240, "DR": 150, "Ast": 243, "TO": 229, "Stl": 263, "Blk": 63, "Fouls": 26, "FG%": 203, "FG3%": 102, "EFG%": 134, "FT%": 137, "OppPoints": 113, "OppFGM": 186, "OppFGA": 186, "OppFGM3": 105, "OppFGA3": 102, "OppFTM": 46, "OppFTA": 33, "OppOR": 147, "OppDR": 107, "OppAst": 111, "OppTO": 278, "OppStl": 302, "OppBlk": 90, "OppFouls": 238, "OppFG%": 175, "OppFG3%": 164, "OppEFG%": 167, "OppFT%": 190, "AdjOE": 178, "AdjDE": 217, "AdjNE": 202, "SOS": 183, "SOV": 174}, "stats": {"Points": 69.714, "Poss": 68.461, "OE": 102.017, "DE": 104.457, "NE": -2.44, "FGM": 24.286, "FGA": 56.464, "FGM3": 7.821, "FGA3": 21.821, "FTM": 13.321, "FTA": 18.893, "OR": 10.75, "DR": 23.25, "Ast": 12.179, "TO": 13.893, "Stl": 5.857, "Blk": 4.179, "Fouls": 21.536, "FG%": 0.433, "FG3%": 0.361, "EFG%": 0.503, "FT%": 0.697, "OppPoints": 71.643, "OppFGM": 24.25, "OppFGA": 55.571, "OppFGM3": 6.571, "OppFGA3": 19.071, "OppFTM": 16.571, "OppFTA": 24.25, "OppOR": 11.929, "OppDR": 23.964, "OppAst": 14.286, "OppTO": 13.179, "OppStl": 5.464, "OppBlk": 3.643, "OppFouls": 18.143, "OppFG%": 0.437, "OppFG3%": 0.345, "OppEFG%": 0.496, "OppFT%": 0.686, "AdjOE": 100.549, "AdjDE": 106.654, "AdjNE": -6.105}, "coach": "pat_kennedy", "win_pct": 0.429, "sos": 0.488, "sov": 0.405, "ordinal_data": {"RPI": 210}, "tournament": null, "similar_teams": [{"id": 1129, "year": 2005, "avg": 0.99, "res": 0.993, "st": 0.987, "er": null}, {"id": 1222, "year": 2012, "avg": 0.989, "res": 0.997, "st": 0.981, "er": null}, {"id": 1325, "year": 2015, "avg": 0.988, "res": 0.996, "st": 0.98, "er": null}, {"id": 1339, "year": 2004, "avg": 0.987, "res": 0.989, "st": 0.985, "er": null}, {"id": 1379, "year": 2005, "avg": 0.987, "res": 0.993, "st": 0.981, "er": null}, {"id": 1253, "year": 2019, "avg": 0.986, "res": 0.995, "st": 0.977, "er": null}, {"id": 1307, "year": 2019, "avg": 0.984, "res": 0.985, "st": 0.984, "er": null}, {"id": 1205, "year": 2008, "avg": 0.984, "res": 0.995, "st": 0.974, "er": null}, {"id": 1226, "year": 2009, "avg": 0.984, "res": 0.99, "st": 0.978, "er": null}, {"id": 1232, "year": 2017, "avg": 0.984, "res": 0.985, "st": 0.983, "er": null}]}