{"id": 1319, "year": 2023, "name": "Northern Arizona", "record": {"overall": [10, 23], "conf": [8, 14], "home": [4, 8], "road": [6, 15], "quad_1": [0, 4], "quad_2": [0, 4], "quad_3": [6, 7], "quad_4": [4, 8]}, "quad_wins": {"1": [], "2": [], "3": [{"opp_id": 1364, "team_score": 63, "opp_score": 54, "team_loc": "H", "date_int": 18, "date_str": "11/18", "conf": false}, {"opp_id": 1334, "team_score": 73, "opp_score": 69, "team_loc": "A", "date_int": 36, "date_str": "12/06", "conf": false}, {"opp_id": 1285, "team_score": 75, "opp_score": 74, "team_loc": "H", "date_int": 66, "date_str": "01/05", "conf": true}, {"opp_id": 1294, "team_score": 85, "opp_score": 82, "team_loc": "A", "date_int": 117, "date_str": "02/25", "conf": true}, {"opp_id": 1186, "team_score": 81, "opp_score": 80, "team_loc": "N", "date_int": 125, "date_str": "03/05", "conf": true}, {"opp_id": 1285, "team_score": 83, "opp_score": 71, "team_loc": "N", "date_int": 127, "date_str": "03/07", "conf": true}], "4": [{"opp_id": 1294, "team_score": 83, "opp_score": 73, "team_loc": "H", "date_int": 89, "date_str": "01/28", "conf": true}, {"opp_id": 1170, "team_score": 77, "opp_score": 55, "team_loc": "H", "date_int": 101, "date_str": "02/09", "conf": true}, {"opp_id": 1225, "team_score": 72, "opp_score": 50, "team_loc": "A", "date_int": 110, "date_str": "02/18", "conf": true}, {"opp_id": 1225, "team_score": 87, "opp_score": 76, "team_loc": "N", "date_int": 124, "date_str": "03/04", "conf": true}]}, "quad_losses": {"1": [{"opp_id": 1277, "team_score": 55, "opp_score": 73, "team_loc": "A", "date_int": 7, "date_str": "11/07", "conf": false}, {"opp_id": 1113, "team_score": 68, "opp_score": 84, "team_loc": "A", "date_int": 10, "date_str": "11/10", "conf": false}, {"opp_id": 1430, "team_score": 69, "opp_score": 73, "team_loc": "A", "date_int": 12, "date_str": "11/12", "conf": false}, {"opp_id": 1400, "team_score": 48, "opp_score": 73, "team_loc": "N", "date_int": 21, "date_str": "11/21", "conf": false}], "2": [{"opp_id": 1430, "team_score": 75, "opp_score": 80, "team_loc": "H", "date_int": 40, "date_str": "12/10", "conf": false}, {"opp_id": 1381, "team_score": 101, "opp_score": 106, "team_loc": "A", "date_int": 47, "date_str": "12/17", "conf": false}, {"opp_id": 1286, "team_score": 68, "opp_score": 69, "team_loc": "A", "date_int": 94, "date_str": "02/02", "conf": true}, {"opp_id": 1186, "team_score": 55, "opp_score": 72, "team_loc": "A", "date_int": 108, "date_str": "02/16", "conf": true}], "3": [{"opp_id": 1337, "team_score": 69, "opp_score": 88, "team_loc": "A", "date_int": 33, "date_str": "12/03", "conf": false}, {"opp_id": 1451, "team_score": 60, "opp_score": 76, "team_loc": "A", "date_int": 61, "date_str": "12/31", "conf": true}, {"opp_id": 1286, "team_score": 54, "opp_score": 69, "team_loc": "H", "date_int": 68, "date_str": "01/07", "conf": true}, {"opp_id": 1170, "team_score": 56, "opp_score": 59, "team_loc": "A", "date_int": 75, "date_str": "01/14", "conf": true}, {"opp_id": 1186, "team_score": 76, "opp_score": 79, "team_loc": "H", "date_int": 82, "date_str": "01/21", "conf": true}, {"opp_id": 1285, "team_score": 66, "opp_score": 67, "team_loc": "A", "date_int": 96, "date_str": "02/04", "conf": true}, {"opp_id": 1286, "team_score": 78, "opp_score": 85, "team_loc": "N", "date_int": 128, "date_str": "03/08", "conf": true}], "4": [{"opp_id": 1410, "team_score": 79, "opp_score": 91, "team_loc": "A", "date_int": 22, "date_str": "11/22", "conf": false}, {"opp_id": 1101, "team_score": 82, "opp_score": 92, "team_loc": "H", "date_int": 27, "date_str": "11/27", "conf": false}, {"opp_id": 1226, "team_score": 53, "opp_score": 79, "team_loc": "A", "date_int": 59, "date_str": "12/29", "conf": true}, {"opp_id": 1340, "team_score": 74, "opp_score": 75, "team_loc": "A", "date_int": 73, "date_str": "01/12", "conf": true}, {"opp_id": 1225, "team_score": 83, "opp_score": 88, "team_loc": "H", "date_int": 80, "date_str": "01/19", "conf": true}, {"opp_id": 1226, "team_score": 70, "opp_score": 75, "team_loc": "H", "date_int": 98, "date_str": "02/06", "conf": true}, {"opp_id": 1340, "team_score": 87, "opp_score": 88, "team_loc": "H", "date_int": 103, "date_str": "02/11", "conf": true}, {"opp_id": 1451, "team_score": 89, "opp_score": 90, "team_loc": "H", "date_int": 119, "date_str": "02/27", "conf": true}]}, "conf": "big_sky", "stat_rankings": {"Points": 126, "Poss": 169, "OE": 126, "DE": 39, "NE": 251, "FGM": 111, "FGA": 65, "FGM3": 74, "FGA3": 113, "FTM": 225, "FTA": 273, "OR": 247, "DR": 285, "Ast": 161, "TO": 318, "Stl": 310, "Blk": 356, "Fouls": 69, "FG%": 225, "FG3%": 104, "FT%": 37, "OppPoints": 46, "OppFGM": 108, "OppFGA": 288, "OppFGM3": 115, "OppFGA3": 195, "OppFTM": 24, "OppFTA": 45, "OppOR": 329, "OppDR": 97, "OppAst": 113, "OppTO": 206, "OppStl": 348, "OppBlk": 170, "OppFouls": 146, "OppFG%": 14, "OppFG3%": 43, "OppFT%": 135, "AdjOE": 180, "AdjDE": 99, "AdjNE": 247, "SOS": 174, "SOV": 86}, "stats": {"Points": 72.545, "Poss": 69.735, "OE": 104.045, "DE": 109.022, "NE": -4.977, "FGM": 26.091, "FGA": 59.727, "FGM3": 8.152, "FGA3": 22.818, "FTM": 12.212, "FTA": 16.364, "OR": 7.636, "DR": 21.455, "Ast": 12.97, "TO": 10.364, "Stl": 5.121, "Blk": 1.455, "Fouls": 18.606, "FG%": 0.436, "FG3%": 0.354, "FT%": 0.76, "OppPoints": 76.212, "OppFGM": 26.394, "OppFGA": 54.667, "OppFGM3": 7.697, "OppFGA3": 21.091, "OppFTM": 15.727, "OppFTA": 21.182, "OppOR": 6.97, "OppDR": 24.0, "OppAst": 13.818, "OppTO": 11.485, "OppStl": 4.97, "OppBlk": 3.152, "OppFouls": 17.364, "OppFG%": 0.483, "OppFG3%": 0.367, "OppFT%": 0.721, "AdjOE": 101.869, "AdjDE": 107.038, "AdjNE": -5.169}, "coach": "shane_burcar", "win_pct": 0.303, "sos": 0.498, "sov": 0.468, "ordinal_data": {"NET": 239}, "tournament": null, "similar_teams": [{"id": 1248, "year": 2019, "avg": 0.984, "res": 0.991, "st": 0.976, "er": null}, {"id": 1229, "year": 2023, "avg": 0.98, "res": 0.987, "st": 0.972, "er": null}, {"id": 1168, "year": 2021, "avg": 0.979, "res": 0.996, "st": 0.962, "er": null}]}