{"id": 1330, "year": 2023, "name": "Old Dominion", "record": [18, 12], "record_conf": [11, 8], "record_home": [11, 4], "record_road": [7, 8], "quad_wins": {"1": [], "2": [{"opp_id": 1202, "opp_name": "Furman", "team_score": 82, "opp_score": 77, "team_loc": "N", "date_int": 18, "date_str": "11/18", "conf": false}, {"opp_id": 1375, "opp_name": "South Alabama", "team_score": 66, "opp_score": 64, "team_loc": "A", "date_int": 87, "date_str": "01/26", "conf": true}], "3": [{"opp_id": 1206, "opp_name": "George Mason", "team_score": 78, "opp_score": 77, "team_loc": "H", "date_int": 51, "date_str": "12/21", "conf": false}, {"opp_id": 1418, "opp_name": "Louisiana", "team_score": 70, "opp_score": 66, "team_loc": "H", "date_int": 61, "date_str": "12/31", "conf": true}, {"opp_id": 1204, "opp_name": "Ga Southern", "team_score": 81, "opp_score": 75, "team_loc": "A", "date_int": 68, "date_str": "01/07", "conf": true}, {"opp_id": 1402, "opp_name": "Texas St", "team_score": 70, "opp_score": 68, "team_loc": "A", "date_int": 103, "date_str": "02/11", "conf": true}, {"opp_id": 1111, "opp_name": "Appalachian St", "team_score": 74, "opp_score": 63, "team_loc": "A", "date_int": 110, "date_str": "02/18", "conf": true}, {"opp_id": 1379, "opp_name": "Southern Miss", "team_score": 69, "opp_score": 64, "team_loc": "H", "date_int": 114, "date_str": "02/22", "conf": true}, {"opp_id": 1267, "opp_name": "Marshall", "team_score": 71, "opp_score": 67, "team_loc": "H", "date_int": 116, "date_str": "02/24", "conf": true}], "4": [{"opp_id": 1271, "opp_name": "MD E Shore", "team_score": 84, "opp_score": 65, "team_loc": "H", "date_int": 7, "date_str": "11/07", "conf": false}, {"opp_id": 1187, "opp_name": "East Carolina", "team_score": 71, "opp_score": 50, "team_loc": "H", "date_int": 26, "date_str": "11/26", "conf": false}, {"opp_id": 1313, "opp_name": "Norfolk St", "team_score": 68, "opp_score": 62, "team_loc": "H", "date_int": 33, "date_str": "12/03", "conf": false}, {"opp_id": 1456, "opp_name": "William & Mary", "team_score": 72, "opp_score": 62, "team_loc": "H", "date_int": 37, "date_str": "12/07", "conf": false}, {"opp_id": 1205, "opp_name": "Gardner Webb", "team_score": 44, "opp_score": 43, "team_loc": "H", "date_int": 40, "date_str": "12/10", "conf": false}, {"opp_id": 1209, "opp_name": "Georgia St", "team_score": 70, "opp_score": 58, "team_loc": "H", "date_int": 80, "date_str": "01/19", "conf": true}, {"opp_id": 1157, "opp_name": "Coastal Car", "team_score": 60, "opp_score": 59, "team_loc": "A", "date_int": 89, "date_str": "01/28", "conf": true}, {"opp_id": 1204, "opp_name": "Ga Southern", "team_score": 64, "opp_score": 58, "team_loc": "H", "date_int": 96, "date_str": "02/04", "conf": true}, {"opp_id": 1209, "opp_name": "Georgia St", "team_score": 63, "opp_score": 60, "team_loc": "A", "date_int": 101, "date_str": "02/09", "conf": true}]}, "quad_losses": {"1": [{"opp_id": 1158, "opp_name": "Col Charleston", "team_score": 60, "opp_score": 75, "team_loc": "A", "date_int": 29, "date_str": "11/29", "conf": false}], "2": [{"opp_id": 1439, "opp_name": "Virginia Tech", "team_score": 71, "opp_score": 75, "team_loc": "N", "date_int": 17, "date_str": "11/17", "conf": false}, {"opp_id": 1267, "opp_name": "Marshall", "team_score": 65, "opp_score": 73, "team_loc": "A", "date_int": 75, "date_str": "01/14", "conf": true}, {"opp_id": 1241, "opp_name": "James Madison", "team_score": 67, "opp_score": 76, "team_loc": "A", "date_int": 108, "date_str": "02/16", "conf": true}], "3": [{"opp_id": 1180, "opp_name": "Drexel", "team_score": 59, "opp_score": 71, "team_loc": "A", "date_int": 11, "date_str": "11/11", "conf": false}, {"opp_id": 1172, "opp_name": "Davidson", "team_score": 61, "opp_score": 66, "team_loc": "N", "date_int": 20, "date_str": "11/20", "conf": false}, {"opp_id": 1407, "opp_name": "Troy", "team_score": 71, "opp_score": 78, "team_loc": "A", "date_int": 66, "date_str": "01/05", "conf": true}, {"opp_id": 1241, "opp_name": "James Madison", "team_score": 73, "opp_score": 78, "team_loc": "H", "date_int": 94, "date_str": "02/02", "conf": true}, {"opp_id": 1402, "opp_name": "Texas St", "team_score": 36, "opp_score": 65, "team_loc": "N", "date_int": 122, "date_str": "03/02", "conf": true}], "4": [{"opp_id": 1117, "opp_name": "Arkansas St", "team_score": 57, "opp_score": 60, "team_loc": "H", "date_int": 59, "date_str": "12/29", "conf": true}, {"opp_id": 1157, "opp_name": "Coastal Car", "team_score": 66, "opp_score": 67, "team_loc": "H", "date_int": 73, "date_str": "01/12", "conf": true}, {"opp_id": 1111, "opp_name": "Appalachian St", "team_score": 58, "opp_score": 72, "team_loc": "H", "date_int": 82, "date_str": "01/21", "conf": true}]}, "tourney_seed": null, "conf": "sun_belt", "stat_rankings": {"Points": 282, "Poss": 295, "OE": 239, "DE": 257, "FGM": 290, "FGA": 211, "FGM3": 342, "FGA3": 339, "FTM": 98, "FTA": 64, "OR": 28, "DR": 119, "Ast": 337, "TO": 280, "Stl": 151, "Blk": 102, "Fouls": 183, "FG%": 300, "FG3%": 272, "FT%": 303, "OppPoints": 302, "OppFGM": 318, "OppFGA": 262, "OppFGM3": 153, "OppFGA3": 72, "OppFTM": 184, "OppFTA": 119, "OppOR": 196, "OppDR": 220, "OppAst": 165, "OppTO": 248, "OppStl": 241, "OppBlk": 34, "OppFouls": 91, "OppFG%": 316, "OppFG3%": 306, "OppFT%": 348, "SOS": 123, "SOV": 36}, "stats": {"Points": 66.7, "Poss": 67.02, "OE": 99.427, "DE": 99.348, "FGM": 23.7, "FGA": 56.767, "FGM3": 5.333, "FGA3": 16.933, "FTM": 13.967, "FTA": 20.533, "OR": 10.433, "DR": 23.633, "Ast": 10.5, "TO": 10.933, "Stl": 6.5, "Blk": 3.667, "Fouls": 16.867, "FG%": 0.421, "FG3%": 0.322, "FT%": 0.677, "OppPoints": 66.467, "OppFGM": 23.067, "OppFGA": 55.5, "OppFGM3": 7.467, "OppFGA3": 23.533, "OppFTM": 12.867, "OppFTA": 19.233, "OppOR": 8.167, "OppDR": 22.5, "OppAst": 13.067, "OppTO": 11.033, "OppStl": 5.9, "OppBlk": 3.933, "OppFouls": 17.9, "OppFG%": 0.418, "OppFG3%": 0.316, "OppFT%": 0.664}, "coach": "jeff_a_jones", "win_pct": 0.6, "sos": 0.515, "sov": 0.511, "ordinal_data": {"NET": 156}}