{"id": 1353, "year": 2007, "name": "Rutgers", "record": {"overall": [9, 19], "conf": [3, 13], "home": [7, 8], "road": [2, 11], "quad_1": [0, 5], "quad_2": [0, 9], "quad_3": [3, 4], "quad_4": [6, 1]}, "quad_wins": {"1": [], "2": [], "3": [{"opp_id": 1304, "team_score": 75, "opp_score": 73, "team_loc": "H", "date_int": 33, "date_str": "12/02", "conf": false}, {"opp_id": 1153, "team_score": 54, "opp_score": 42, "team_loc": "A", "date_int": 69, "date_str": "01/07", "conf": true}, {"opp_id": 1371, "team_score": 74, "opp_score": 70, "team_loc": "H", "date_int": 89, "date_str": "01/27", "conf": true}], "4": [{"opp_id": 1306, "team_score": 55, "opp_score": 48, "team_loc": "H", "date_int": 37, "date_str": "12/06", "conf": false}, {"opp_id": 1343, "team_score": 53, "opp_score": 47, "team_loc": "A", "date_int": 40, "date_str": "12/09", "conf": false}, {"opp_id": 1233, "team_score": 66, "opp_score": 51, "team_loc": "H", "date_int": 47, "date_str": "12/16", "conf": false}, {"opp_id": 1250, "team_score": 67, "opp_score": 61, "team_loc": "H", "date_int": 53, "date_str": "12/22", "conf": false}, {"opp_id": 1354, "team_score": 75, "opp_score": 68, "team_loc": "H", "date_int": 62, "date_str": "12/31", "conf": false}, {"opp_id": 1153, "team_score": 73, "opp_score": 69, "team_loc": "H", "date_int": 103, "date_str": "02/10", "conf": true}]}, "quad_losses": {"1": [{"opp_id": 1133, "team_score": 72, "opp_score": 101, "team_loc": "N", "date_int": 25, "date_str": "11/24", "conf": false}, {"opp_id": 1314, "team_score": 48, "opp_score": 87, "team_loc": "A", "date_int": 59, "date_str": "12/28", "conf": false}, {"opp_id": 1207, "team_score": 54, "opp_score": 68, "team_loc": "H", "date_int": 79, "date_str": "01/17", "conf": true}, {"opp_id": 1266, "team_score": 47, "opp_score": 67, "team_loc": "A", "date_int": 100, "date_str": "02/07", "conf": true}, {"opp_id": 1437, "team_score": 51, "opp_score": 74, "team_loc": "A", "date_int": 117, "date_str": "02/24", "conf": true}], "2": [{"opp_id": 1243, "team_score": 41, "opp_score": 55, "team_loc": "H", "date_int": 16, "date_str": "11/15", "conf": false}, {"opp_id": 1275, "team_score": 44, "opp_score": 57, "team_loc": "N", "date_int": 26, "date_str": "11/25", "conf": false}, {"opp_id": 1393, "team_score": 58, "opp_score": 68, "team_loc": "H", "date_int": 72, "date_str": "01/10", "conf": true}, {"opp_id": 1177, "team_score": 37, "opp_score": 60, "team_loc": "H", "date_int": 75, "date_str": "01/13", "conf": true}, {"opp_id": 1344, "team_score": 63, "opp_score": 78, "team_loc": "A", "date_int": 82, "date_str": "01/20", "conf": true}, {"opp_id": 1452, "team_score": 83, "opp_score": 89, "team_loc": "H", "date_int": 93, "date_str": "01/31", "conf": true}, {"opp_id": 1163, "team_score": 50, "opp_score": 61, "team_loc": "A", "date_int": 96, "date_str": "02/03", "conf": true}, {"opp_id": 1385, "team_score": 55, "opp_score": 60, "team_loc": "A", "date_int": 108, "date_str": "02/15", "conf": true}, {"opp_id": 1323, "team_score": 66, "opp_score": 73, "team_loc": "H", "date_int": 124, "date_str": "03/03", "conf": true}], "3": [{"opp_id": 1396, "team_score": 54, "opp_score": 77, "team_loc": "A", "date_int": 30, "date_str": "11/29", "conf": false}, {"opp_id": 1371, "team_score": 72, "opp_score": 77, "team_loc": "A", "date_int": 65, "date_str": "01/03", "conf": true}, {"opp_id": 1378, "team_score": 40, "opp_score": 62, "team_loc": "A", "date_int": 86, "date_str": "01/24", "conf": true}, {"opp_id": 1163, "team_score": 55, "opp_score": 65, "team_loc": "H", "date_int": 114, "date_str": "02/21", "conf": true}], "4": [{"opp_id": 1238, "team_score": 70, "opp_score": 71, "team_loc": "H", "date_int": 22, "date_str": "11/21", "conf": false}]}, "conf": "big_east", "stat_rankings": {"Points": 316, "Poss": 310, "OE": 289, "DE": 278, "NE": 301, "FGM": 322, "FGA": 253, "FGM3": 291, "FGA3": 223, "FTM": 184, "FTA": 158, "OR": 113, "DR": 267, "Ast": 334, "TO": 269, "Stl": 331, "Blk": 63, "Fouls": 187, "FG%": 327, "FG3%": 293, "EFG%": 324, "FT%": 221, "OppPoints": 210, "OppFGM": 181, "OppFGA": 218, "OppFGM3": 138, "OppFGA3": 265, "OppFTM": 239, "OppFTA": 266, "OppOR": 209, "OppDR": 113, "OppAst": 101, "OppTO": 318, "OppStl": 268, "OppBlk": 23, "OppFouls": 139, "OppFG%": 119, "OppFG3%": 24, "OppEFG%": 122, "OppFT%": 22, "AdjOE": 222, "AdjDE": 128, "AdjNE": 169, "SOS": 83, "SOV": 246}, "stats": {"Points": 59.0, "Poss": 62.822, "OE": 93.827, "DE": 106.752, "NE": -12.925, "FGM": 20.107, "FGA": 52.357, "FGM3": 5.179, "FGA3": 17.143, "FTM": 13.607, "FTA": 20.179, "OR": 12.071, "DR": 21.25, "Ast": 8.821, "TO": 13.0, "Stl": 4.321, "Blk": 4.107, "Fouls": 18.393, "FG%": 0.388, "FG3%": 0.309, "EFG%": 0.439, "FT%": 0.669, "OppPoints": 67.107, "OppFGM": 23.929, "OppFGA": 53.321, "OppFGM3": 6.679, "OppFGA3": 16.821, "OppFTM": 12.571, "OppFTA": 17.643, "OppOR": 10.964, "OppDR": 23.571, "OppAst": 14.214, "OppTO": 12.036, "OppStl": 5.786, "OppBlk": 4.393, "OppFouls": 19.0, "OppFG%": 0.451, "OppFG3%": 0.388, "OppEFG%": 0.513, "OppFT%": 0.723, "AdjOE": 96.806, "AdjDE": 99.148, "AdjNE": -2.342}, "coach": "fred_hill", "win_pct": 0.321, "sos": 0.534, "sov": 0.362, "ordinal_data": {"RPI": 215}, "tournament": null, "similar_teams": [{"id": 1334, "year": 2015, "avg": 0.984, "res": 0.988, "st": 0.981, "er": null}, {"id": 1362, "year": 2006, "avg": 0.984, "res": 0.993, "st": 0.974, "er": null}, {"id": 1444, "year": 2006, "avg": 0.983, "res": 0.992, "st": 0.973, "er": null}, {"id": 1333, "year": 2007, "avg": 0.981, "res": 0.997, "st": 0.966, "er": null}, {"id": 1178, "year": 2007, "avg": 0.981, "res": 0.998, "st": 0.964, "er": null}, {"id": 1283, "year": 2009, "avg": 0.981, "res": 0.99, "st": 0.972, "er": null}, {"id": 1403, "year": 2013, "avg": 0.981, "res": 0.987, "st": 0.974, "er": null}, {"id": 1353, "year": 2014, "avg": 0.981, "res": 0.993, "st": 0.969, "er": null}, {"id": 1127, "year": 2005, "avg": 0.98, "res": 0.992, "st": 0.968, "er": null}, {"id": 1336, "year": 2005, "avg": 0.98, "res": 0.991, "st": 0.969, "er": null}]}