{"id": 1365, "year": 2007, "name": "Santa Clara", "record": {"overall": [20, 10], "conf": [11, 5], "home": [11, 4], "road": [9, 6], "quad_1": [2, 4], "quad_2": [1, 3], "quad_3": [8, 1], "quad_4": [9, 2]}, "quad_wins": {"1": [{"opp_id": 1390, "team_score": 62, "opp_score": 46, "team_loc": "A", "date_int": 47, "date_str": "12/16", "conf": false}, {"opp_id": 1211, "team_score": 84, "opp_score": 73, "team_loc": "A", "date_int": 105, "date_str": "02/12", "conf": true}], "2": [{"opp_id": 1429, "team_score": 77, "opp_score": 75, "team_loc": "H", "date_int": 54, "date_str": "12/23", "conf": false}], "3": [{"opp_id": 1428, "team_score": 83, "opp_score": 72, "team_loc": "H", "date_int": 19, "date_str": "11/18", "conf": false}, {"opp_id": 1218, "team_score": 68, "opp_score": 59, "team_loc": "H", "date_int": 30, "date_str": "11/29", "conf": false}, {"opp_id": 1334, "team_score": 67, "opp_score": 49, "team_loc": "A", "date_int": 40, "date_str": "12/09", "conf": false}, {"opp_id": 1388, "team_score": 76, "opp_score": 69, "team_loc": "H", "date_int": 68, "date_str": "01/06", "conf": true}, {"opp_id": 1360, "team_score": 61, "opp_score": 47, "team_loc": "A", "date_int": 82, "date_str": "01/20", "conf": true}, {"opp_id": 1362, "team_score": 61, "opp_score": 58, "team_loc": "A", "date_int": 84, "date_str": "01/22", "conf": true}, {"opp_id": 1388, "team_score": 63, "opp_score": 57, "team_loc": "A", "date_int": 96, "date_str": "02/03", "conf": true}, {"opp_id": 1388, "team_score": 63, "opp_score": 47, "team_loc": "N", "date_int": 125, "date_str": "03/04", "conf": true}], "4": [{"opp_id": 1363, "team_score": 71, "opp_score": 53, "team_loc": "H", "date_int": 28, "date_str": "11/27", "conf": false}, {"opp_id": 1106, "team_score": 71, "opp_score": 45, "team_loc": "N", "date_int": 32, "date_str": "12/01", "conf": false}, {"opp_id": 1186, "team_score": 91, "opp_score": 68, "team_loc": "H", "date_int": 42, "date_str": "12/11", "conf": false}, {"opp_id": 1159, "team_score": 53, "opp_score": 39, "team_loc": "H", "date_int": 59, "date_str": "12/28", "conf": false}, {"opp_id": 1339, "team_score": 57, "opp_score": 41, "team_loc": "H", "date_int": 77, "date_str": "01/15", "conf": true}, {"opp_id": 1337, "team_score": 77, "opp_score": 55, "team_loc": "H", "date_int": 91, "date_str": "01/29", "conf": true}, {"opp_id": 1362, "team_score": 74, "opp_score": 62, "team_loc": "H", "date_int": 98, "date_str": "02/05", "conf": true}, {"opp_id": 1339, "team_score": 76, "opp_score": 53, "team_loc": "A", "date_int": 103, "date_str": "02/10", "conf": true}, {"opp_id": 1360, "team_score": 80, "opp_score": 72, "team_loc": "H", "date_int": 110, "date_str": "02/17", "conf": true}]}, "quad_losses": {"1": [{"opp_id": 1305, "team_score": 70, "opp_score": 78, "team_loc": "H", "date_int": 26, "date_str": "11/25", "conf": false}, {"opp_id": 1283, "team_score": 51, "opp_score": 78, "team_loc": "A", "date_int": 33, "date_str": "12/02", "conf": false}, {"opp_id": 1246, "team_score": 60, "opp_score": 74, "team_loc": "A", "date_int": 50, "date_str": "12/19", "conf": false}, {"opp_id": 1102, "team_score": 48, "opp_score": 78, "team_loc": "H", "date_int": 60, "date_str": "12/29", "conf": false}], "2": [{"opp_id": 1143, "team_score": 48, "opp_score": 73, "team_loc": "A", "date_int": 21, "date_str": "11/20", "conf": false}, {"opp_id": 1211, "team_score": 69, "opp_score": 77, "team_loc": "H", "date_int": 75, "date_str": "01/13", "conf": true}, {"opp_id": 1211, "team_score": 68, "opp_score": 77, "team_loc": "N", "date_int": 126, "date_str": "03/05", "conf": true}], "3": [{"opp_id": 1258, "team_score": 66, "opp_score": 67, "team_loc": "A", "date_int": 117, "date_str": "02/24", "conf": true}], "4": [{"opp_id": 1258, "team_score": 71, "opp_score": 74, "team_loc": "H", "date_int": 89, "date_str": "01/27", "conf": true}, {"opp_id": 1337, "team_score": 82, "opp_score": 89, "team_loc": "A", "date_int": 119, "date_str": "02/26", "conf": true}]}, "conf": "wcc", "stat_rankings": {"Points": 173, "Poss": 242, "OE": 125, "DE": 283, "NE": 73, "FGM": 110, "FGA": 188, "FGM3": 172, "FGA3": 214, "FTM": 289, "FTA": 283, "OR": 155, "DR": 62, "Ast": 67, "TO": 155, "Stl": 301, "Blk": 164, "Fouls": 202, "FG%": 59, "FG3%": 67, "EFG%": 84, "FT%": 264, "OppPoints": 283, "OppFGM": 296, "OppFGA": 195, "OppFGM3": 159, "OppFGA3": 112, "OppFTM": 176, "OppFTA": 212, "OppOR": 241, "OppDR": 284, "OppAst": 207, "OppTO": 276, "OppStl": 168, "OppBlk": 285, "OppFouls": 287, "OppFG%": 320, "OppFG3%": 272, "OppEFG%": 306, "OppFT%": 24, "AdjOE": 91, "AdjDE": 172, "AdjNE": 62, "SOS": 162, "SOV": 128}, "stats": {"Points": 68.267, "Poss": 65.705, "OE": 104.151, "DE": 96.218, "NE": 7.933, "FGM": 25.2, "FGA": 54.5, "FGM3": 6.367, "FGA3": 17.4, "FTM": 11.5, "FTA": 17.3, "OR": 11.5, "DR": 24.233, "Ast": 14.9, "TO": 14.733, "Stl": 5.2, "Blk": 3.1, "Fouls": 18.167, "FG%": 0.466, "FG3%": 0.374, "EFG%": 0.526, "FT%": 0.654, "OppPoints": 63.5, "OppFGM": 21.633, "OppFGA": 54.133, "OppFGM3": 6.567, "OppFGA3": 19.767, "OppFTM": 13.667, "OppFTA": 19.0, "OppOR": 10.633, "OppDR": 20.667, "OppAst": 12.833, "OppTO": 12.933, "OppStl": 6.733, "OppBlk": 2.6, "OppFouls": 17.067, "OppFG%": 0.399, "OppFG3%": 0.328, "OppEFG%": 0.46, "OppFT%": 0.722, "AdjOE": 108.553, "AdjDE": 102.166, "AdjNE": 6.387}, "coach": "dick_davey", "win_pct": 0.667, "sos": 0.496, "sov": 0.43, "ordinal_data": {"RPI": 99}, "tournament": null, "similar_teams": [{"id": 1177, "year": 2005, "avg": 0.987, "res": 0.992, "st": 0.982, "er": null}, {"id": 1138, "year": 2012, "avg": 0.986, "res": 0.99, "st": 0.982, "er": null}, {"id": 1397, "year": 2003, "avg": 0.985, "res": 0.986, "st": 0.984, "er": null}]}