{"id": 1389, "year": 2008, "name": "St Peter's", "record": {"overall": [6, 24], "conf": [3, 16], "home": [5, 9], "road": [1, 15], "quad_1": [0, 1], "quad_2": [0, 7], "quad_3": [1, 8], "quad_4": [5, 8]}, "quad_wins": {"1": [], "2": [], "3": [{"opp_id": 1447, "team_score": 72, "opp_score": 69, "team_loc": "H", "date_int": 12, "date_str": "11/17", "conf": false}], "4": [{"opp_id": 1353, "team_score": 65, "opp_score": 58, "team_loc": "H", "date_int": 20, "date_str": "11/25", "conf": false}, {"opp_id": 1284, "team_score": 72, "opp_score": 62, "team_loc": "H", "date_int": 23, "date_str": "11/28", "conf": false}, {"opp_id": 1145, "team_score": 65, "opp_score": 54, "team_loc": "H", "date_int": 60, "date_str": "01/04", "conf": true}, {"opp_id": 1264, "team_score": 78, "opp_score": 68, "team_loc": "H", "date_int": 90, "date_str": "02/03", "conf": true}, {"opp_id": 1145, "team_score": 75, "opp_score": 68, "team_loc": "A", "date_int": 103, "date_str": "02/16", "conf": true}]}, "quad_losses": {"1": [{"opp_id": 1373, "team_score": 56, "opp_score": 79, "team_loc": "A", "date_int": 62, "date_str": "01/06", "conf": true}], "2": [{"opp_id": 1420, "team_score": 78, "opp_score": 81, "team_loc": "A", "date_int": 5, "date_str": "11/10", "conf": false}, {"opp_id": 1371, "team_score": 75, "opp_score": 85, "team_loc": "A", "date_int": 29, "date_str": "12/04", "conf": false}, {"opp_id": 1344, "team_score": 78, "opp_score": 83, "team_loc": "A", "date_int": 56, "date_str": "12/31", "conf": false}, {"opp_id": 1265, "team_score": 71, "opp_score": 86, "team_loc": "A", "date_int": 67, "date_str": "01/11", "conf": true}, {"opp_id": 1310, "team_score": 69, "opp_score": 71, "team_loc": "A", "date_int": 105, "date_str": "02/18", "conf": true}, {"opp_id": 1351, "team_score": 76, "opp_score": 88, "team_loc": "A", "date_int": 116, "date_str": "02/29", "conf": true}, {"opp_id": 1373, "team_score": 64, "opp_score": 77, "team_loc": "H", "date_int": 118, "date_str": "03/02", "conf": true}], "3": [{"opp_id": 1254, "team_score": 62, "opp_score": 67, "team_loc": "A", "date_int": 45, "date_str": "12/20", "conf": false}, {"opp_id": 1233, "team_score": 50, "opp_score": 69, "team_loc": "A", "date_int": 69, "date_str": "01/13", "conf": true}, {"opp_id": 1259, "team_score": 57, "opp_score": 62, "team_loc": "H", "date_int": 75, "date_str": "01/19", "conf": true}, {"opp_id": 1193, "team_score": 64, "opp_score": 70, "team_loc": "A", "date_int": 77, "date_str": "01/21", "conf": true}, {"opp_id": 1310, "team_score": 59, "opp_score": 79, "team_loc": "H", "date_int": 81, "date_str": "01/25", "conf": true}, {"opp_id": 1351, "team_score": 67, "opp_score": 76, "team_loc": "H", "date_int": 83, "date_str": "01/27", "conf": true}, {"opp_id": 1259, "team_score": 69, "opp_score": 81, "team_loc": "A", "date_int": 94, "date_str": "02/07", "conf": true}, {"opp_id": 1265, "team_score": 61, "opp_score": 69, "team_loc": "H", "date_int": 97, "date_str": "02/10", "conf": true}], "4": [{"opp_id": 1250, "team_score": 56, "opp_score": 60, "team_loc": "A", "date_int": 9, "date_str": "11/14", "conf": false}, {"opp_id": 1404, "team_score": 74, "opp_score": 78, "team_loc": "H", "date_int": 26, "date_str": "12/01", "conf": false}, {"opp_id": 1264, "team_score": 62, "opp_score": 65, "team_loc": "A", "date_int": 32, "date_str": "12/07", "conf": true}, {"opp_id": 1192, "team_score": 74, "opp_score": 85, "team_loc": "A", "date_int": 47, "date_str": "12/22", "conf": false}, {"opp_id": 1193, "team_score": 78, "opp_score": 89, "team_loc": "H", "date_int": 53, "date_str": "12/28", "conf": true}, {"opp_id": 1233, "team_score": 52, "opp_score": 60, "team_loc": "H", "date_int": 88, "date_str": "02/01", "conf": true}, {"opp_id": 1131, "team_score": 64, "opp_score": 67, "team_loc": "H", "date_int": 110, "date_str": "02/23", "conf": false}, {"opp_id": 1264, "team_score": 59, "opp_score": 73, "team_loc": "N", "date_int": 123, "date_str": "03/07", "conf": true}]}, "conf": "maac", "stat_rankings": {"Points": 210, "Poss": 100, "OE": 270, "DE": 232, "NE": 266, "FGM": 169, "FGA": 61, "FGM3": 142, "FGA3": 125, "FTM": 290, "FTA": 272, "OR": 40, "DR": 121, "Ast": 320, "TO": 64, "Stl": 107, "Blk": 51, "Fouls": 95, "FG%": 287, "FG3%": 201, "EFG%": 286, "FT%": 260, "OppPoints": 87, "OppFGM": 105, "OppFGA": 74, "OppFGM3": 157, "OppFGA3": 153, "OppFTM": 97, "OppFTA": 63, "OppOR": 37, "OppDR": 80, "OppAst": 62, "OppTO": 198, "OppStl": 25, "OppBlk": 32, "OppFouls": 264, "OppFG%": 179, "OppFG3%": 153, "OppEFG%": 186, "OppFT%": 272, "AdjOE": 261, "AdjDE": 215, "AdjNE": 244, "SOS": 181, "SOV": 313}, "stats": {"Points": 66.733, "Poss": 69.797, "OE": 95.588, "DE": 104.22, "NE": -8.632, "FGM": 24.0, "FGA": 58.667, "FGM3": 6.933, "FGA3": 20.0, "FTM": 11.8, "FTA": 17.733, "OR": 13.233, "DR": 23.733, "Ast": 10.4, "TO": 16.1, "Stl": 7.3, "Blk": 4.467, "Fouls": 19.767, "FG%": 0.411, "FG3%": 0.343, "EFG%": 0.47, "FT%": 0.66, "OppPoints": 72.633, "OppFGM": 25.4, "OppFGA": 58.033, "OppFGM3": 6.767, "OppFGA3": 19.233, "OppFTM": 15.067, "OppFTA": 22.533, "OppOR": 13.033, "OppDR": 24.6, "OppAst": 14.767, "OppTO": 13.933, "OppStl": 8.333, "OppBlk": 4.167, "OppFouls": 17.533, "OppFG%": 0.439, "OppFG3%": 0.354, "OppEFG%": 0.498, "OppFT%": 0.664, "AdjOE": 94.647, "AdjDE": 106.508, "AdjNE": -11.861}, "coach": "john_dunne", "win_pct": 0.2, "sos": 0.491, "sov": 0.349, "ordinal_data": {"RPI": 315}, "tournament": null, "similar_teams": [{"id": 1145, "year": 2008, "avg": 0.993, "res": 0.996, "st": 0.989, "er": null}, {"id": 1367, "year": 2010, "avg": 0.991, "res": 0.998, "st": 0.985, "er": null}, {"id": 1405, "year": 2009, "avg": 0.99, "res": 0.998, "st": 0.983, "er": null}]}