{"id": 1460, "year": 2010, "name": "Wright St", "record": {"overall": [20, 12], "conf": [13, 7], "home": [12, 1], "road": [8, 11], "quad_1": [0, 6], "quad_2": [1, 3], "quad_3": [6, 3], "quad_4": [13, 0]}, "quad_wins": {"1": [], "2": [{"opp_id": 1358, "team_score": 88, "opp_score": 48, "team_loc": "H", "date_int": 56, "date_str": "12/28", "conf": false}], "3": [{"opp_id": 1125, "team_score": 82, "opp_score": 73, "team_loc": "N", "date_int": 13, "date_str": "11/15", "conf": false}, {"opp_id": 1178, "team_score": 61, "opp_score": 59, "team_loc": "A", "date_int": 82, "date_str": "01/23", "conf": true}, {"opp_id": 1434, "team_score": 75, "opp_score": 71, "team_loc": "A", "date_int": 94, "date_str": "02/04", "conf": true}, {"opp_id": 1454, "team_score": 68, "opp_score": 63, "team_loc": "H", "date_int": 101, "date_str": "02/11", "conf": true}, {"opp_id": 1453, "team_score": 67, "opp_score": 54, "team_loc": "H", "date_int": 103, "date_str": "02/13", "conf": true}, {"opp_id": 1178, "team_score": 69, "opp_score": 50, "team_loc": "N", "date_int": 124, "date_str": "03/06", "conf": true}], "4": [{"opp_id": 1340, "team_score": 75, "opp_score": 70, "team_loc": "N", "date_int": 12, "date_str": "11/14", "conf": false}, {"opp_id": 1141, "team_score": 69, "opp_score": 53, "team_loc": "H", "date_int": 22, "date_str": "11/24", "conf": false}, {"opp_id": 1156, "team_score": 73, "opp_score": 64, "team_loc": "H", "date_int": 31, "date_str": "12/03", "conf": true}, {"opp_id": 1464, "team_score": 67, "opp_score": 54, "team_loc": "H", "date_int": 33, "date_str": "12/05", "conf": true}, {"opp_id": 1405, "team_score": 66, "opp_score": 56, "team_loc": "A", "date_int": 36, "date_str": "12/08", "conf": false}, {"opp_id": 1271, "team_score": 87, "opp_score": 46, "team_loc": "H", "date_int": 47, "date_str": "12/19", "conf": false}, {"opp_id": 1114, "team_score": 69, "opp_score": 47, "team_loc": "H", "date_int": 50, "date_str": "12/22", "conf": false}, {"opp_id": 1227, "team_score": 64, "opp_score": 47, "team_loc": "A", "date_int": 61, "date_str": "01/02", "conf": true}, {"opp_id": 1434, "team_score": 59, "opp_score": 57, "team_loc": "H", "date_int": 69, "date_str": "01/10", "conf": true}, {"opp_id": 1227, "team_score": 79, "opp_score": 43, "team_loc": "H", "date_int": 87, "date_str": "01/28", "conf": true}, {"opp_id": 1260, "team_score": 66, "opp_score": 48, "team_loc": "H", "date_int": 89, "date_str": "01/30", "conf": true}, {"opp_id": 1178, "team_score": 70, "opp_score": 53, "team_loc": "H", "date_int": 107, "date_str": "02/17", "conf": true}, {"opp_id": 1464, "team_score": 76, "opp_score": 73, "team_loc": "A", "date_int": 115, "date_str": "02/25", "conf": true}]}, "quad_losses": {"1": [{"opp_id": 1449, "team_score": 69, "opp_score": 74, "team_loc": "A", "date_int": 11, "date_str": "11/13", "conf": false}, {"opp_id": 1318, "team_score": 67, "opp_score": 70, "team_loc": "A", "date_int": 26, "date_str": "11/28", "conf": false}, {"opp_id": 1280, "team_score": 69, "opp_score": 80, "team_loc": "A", "date_int": 44, "date_str": "12/16", "conf": false}, {"opp_id": 1139, "team_score": 65, "opp_score": 77, "team_loc": "H", "date_int": 67, "date_str": "01/08", "conf": true}, {"opp_id": 1139, "team_score": 62, "opp_score": 74, "team_loc": "A", "date_int": 96, "date_str": "02/06", "conf": true}, {"opp_id": 1139, "team_score": 45, "opp_score": 70, "team_loc": "A", "date_int": 127, "date_str": "03/09", "conf": true}], "2": [{"opp_id": 1453, "team_score": 66, "opp_score": 68, "team_loc": "A", "date_int": 73, "date_str": "01/14", "conf": true}, {"opp_id": 1454, "team_score": 61, "opp_score": 67, "team_loc": "A", "date_int": 75, "date_str": "01/16", "conf": true}, {"opp_id": 1325, "team_score": 59, "opp_score": 64, "team_loc": "A", "date_int": 110, "date_str": "02/20", "conf": false}], "3": [{"opp_id": 1275, "team_score": 55, "opp_score": 56, "team_loc": "A", "date_int": 41, "date_str": "12/13", "conf": false}, {"opp_id": 1260, "team_score": 52, "opp_score": 53, "team_loc": "A", "date_int": 59, "date_str": "12/31", "conf": true}, {"opp_id": 1156, "team_score": 63, "opp_score": 68, "team_loc": "A", "date_int": 117, "date_str": "02/27", "conf": true}], "4": []}, "conf": "horizon", "stat_rankings": {"Points": 183, "Poss": 319, "OE": 68, "DE": 65, "NE": 53, "FGM": 195, "FGA": 265, "FGM3": 55, "FGA3": 65, "FTM": 253, "FTA": 296, "OR": 267, "DR": 338, "Ast": 117, "TO": 307, "Stl": 238, "Blk": 319, "Fouls": 152, "FG%": 116, "FG3%": 61, "EFG%": 67, "FT%": 25, "OppPoints": 327, "OppFGM": 337, "OppFGA": 342, "OppFGM3": 271, "OppFGA3": 306, "OppFTM": 141, "OppFTA": 180, "OppOR": 338, "OppDR": 280, "OppAst": 305, "OppTO": 47, "OppStl": 336, "OppBlk": 325, "OppFouls": 215, "OppFG%": 160, "OppFG3%": 105, "OppEFG%": 157, "OppFT%": 9, "AdjOE": 78, "AdjDE": 81, "AdjNE": 76, "SOS": 154, "SOV": 144}, "stats": {"Points": 67.594, "Poss": 63.174, "OE": 107.1, "DE": 96.477, "NE": 10.623, "FGM": 23.438, "FGA": 52.875, "FGM3": 7.5, "FGA3": 20.5, "FTM": 13.219, "FTA": 18.031, "OR": 10.125, "DR": 20.0, "Ast": 13.531, "TO": 11.719, "Stl": 5.938, "Blk": 1.969, "Fouls": 18.906, "FG%": 0.445, "FG3%": 0.369, "EFG%": 0.516, "FT%": 0.74, "OppPoints": 60.938, "OppFGM": 20.25, "OppFGA": 46.5, "OppFGM3": 5.438, "OppFGA3": 15.312, "OppFTM": 15.0, "OppFTA": 20.531, "OppOR": 8.594, "OppDR": 21.906, "OppAst": 11.0, "OppTO": 15.656, "OppStl": 4.969, "OppBlk": 2.469, "OppFouls": 18.219, "OppFG%": 0.437, "OppFG3%": 0.354, "OppEFG%": 0.496, "OppFT%": 0.735, "AdjOE": 109.153, "AdjDE": 93.923, "AdjNE": 15.23}, "coach": "brad_brownell", "win_pct": 0.625, "sos": 0.504, "sov": 0.419, "ordinal_data": {"RPI": 80}, "tournament": null, "similar_teams": [{"id": 1283, "year": 2010, "avg": 0.992, "res": 0.997, "st": 0.987, "er": null}, {"id": 1451, "year": 2010, "avg": 0.99, "res": 1.0, "st": 0.98, "er": null}, {"id": 1107, "year": 2007, "avg": 0.988, "res": 0.992, "st": 0.983, "er": "First Round"}]}